{
  "property": "sc-domain:kogan-disalvo.com",
  "dateRange": {
    "start": "2026-01-04",
    "end": "2026-04-04"
  },
  "totals": {
    "clicks": 7223,
    "impressions": 3091093,
    "ctr": 0.002336713906699022,
    "position": 21.568622495264076
  },
  "dailyData": [
    {
      "date": "2026-01-04",
      "clicks": 47,
      "impressions": 20552,
      "ctr": 0.0022868820552744257,
      "position": 26.42467886337096
    },
    {
      "date": "2026-01-05",
      "clicks": 74,
      "impressions": 44550,
      "ctr": 0.0016610549943883277,
      "position": 13.240852974186307
    },
    {
      "date": "2026-01-06",
      "clicks": 63,
      "impressions": 22999,
      "ctr": 0.0027392495325883736,
      "position": 21.57354667594243
    },
    {
      "date": "2026-01-07",
      "clicks": 92,
      "impressions": 39586,
      "ctr": 0.002324053958470166,
      "position": 31.428030111655637
    },
    {
      "date": "2026-01-08",
      "clicks": 94,
      "impressions": 40172,
      "ctr": 0.002339938265458528,
      "position": 25.901498556208303
    },
    {
      "date": "2026-01-09",
      "clicks": 87,
      "impressions": 32953,
      "ctr": 0.0026401238127029404,
      "position": 29.801747944041512
    },
    {
      "date": "2026-01-10",
      "clicks": 38,
      "impressions": 24715,
      "ctr": 0.0015375278171151122,
      "position": 31.75601861217884
    },
    {
      "date": "2026-01-11",
      "clicks": 42,
      "impressions": 29078,
      "ctr": 0.0014443909484833895,
      "position": 30.126005915124836
    },
    {
      "date": "2026-01-12",
      "clicks": 90,
      "impressions": 43621,
      "ctr": 0.0020632264276380643,
      "position": 15.016987230920886
    },
    {
      "date": "2026-01-13",
      "clicks": 76,
      "impressions": 32504,
      "ctr": 0.002338173763229141,
      "position": 23.246092788579865
    },
    {
      "date": "2026-01-14",
      "clicks": 88,
      "impressions": 29304,
      "ctr": 0.003003003003003003,
      "position": 26.957753207753207
    },
    {
      "date": "2026-01-15",
      "clicks": 87,
      "impressions": 27495,
      "ctr": 0.003164211674849973,
      "position": 19.513366066557555
    },
    {
      "date": "2026-01-16",
      "clicks": 73,
      "impressions": 25774,
      "ctr": 0.0028323116318770855,
      "position": 24.313921005664625
    },
    {
      "date": "2026-01-17",
      "clicks": 30,
      "impressions": 24739,
      "ctr": 0.0012126601721977445,
      "position": 26.57431585755285
    },
    {
      "date": "2026-01-18",
      "clicks": 46,
      "impressions": 28969,
      "ctr": 0.0015879043115054024,
      "position": 28.335841761883394
    },
    {
      "date": "2026-01-19",
      "clicks": 60,
      "impressions": 37611,
      "ctr": 0.0015952779771875249,
      "position": 21.753476376591955
    },
    {
      "date": "2026-01-20",
      "clicks": 100,
      "impressions": 32514,
      "ctr": 0.0030755982038506487,
      "position": 24.69791474441779
    },
    {
      "date": "2026-01-21",
      "clicks": 126,
      "impressions": 33737,
      "ctr": 0.0037347719121439368,
      "position": 23.805465809052375
    },
    {
      "date": "2026-01-22",
      "clicks": 111,
      "impressions": 32207,
      "ctr": 0.0034464557394355264,
      "position": 23.468128046697924
    },
    {
      "date": "2026-01-23",
      "clicks": 106,
      "impressions": 28329,
      "ctr": 0.0037417487380422888,
      "position": 22.77270641392213
    },
    {
      "date": "2026-01-24",
      "clicks": 35,
      "impressions": 27979,
      "ctr": 0.0012509382036527395,
      "position": 25.32388577147146
    },
    {
      "date": "2026-01-25",
      "clicks": 43,
      "impressions": 66425,
      "ctr": 0.0006473466315393301,
      "position": 15.28210764019571
    },
    {
      "date": "2026-01-26",
      "clicks": 105,
      "impressions": 43516,
      "ctr": 0.0024129055979409874,
      "position": 21.848262707969482
    },
    {
      "date": "2026-01-27",
      "clicks": 107,
      "impressions": 41717,
      "ctr": 0.002564901598868567,
      "position": 23.998969245151855
    },
    {
      "date": "2026-01-28",
      "clicks": 109,
      "impressions": 37743,
      "ctr": 0.002887952732957105,
      "position": 22.919428768248416
    },
    {
      "date": "2026-01-29",
      "clicks": 100,
      "impressions": 35717,
      "ctr": 0.002799787216171571,
      "position": 22.16501945852115
    },
    {
      "date": "2026-01-30",
      "clicks": 92,
      "impressions": 38304,
      "ctr": 0.0024018379281537175,
      "position": 22.98467522974102
    },
    {
      "date": "2026-01-31",
      "clicks": 52,
      "impressions": 35244,
      "ctr": 0.0014754284417205765,
      "position": 24.201849960276927
    },
    {
      "date": "2026-02-01",
      "clicks": 49,
      "impressions": 50329,
      "ctr": 0.0009735937531045719,
      "position": 27.55973693099406
    },
    {
      "date": "2026-02-02",
      "clicks": 116,
      "impressions": 46445,
      "ctr": 0.002497577780170094,
      "position": 21.90933362041124
    },
    {
      "date": "2026-02-03",
      "clicks": 125,
      "impressions": 31543,
      "ctr": 0.003962844371175855,
      "position": 20.74989696604635
    },
    {
      "date": "2026-02-04",
      "clicks": 114,
      "impressions": 36528,
      "ctr": 0.0031208935611038106,
      "position": 22.071315155497153
    },
    {
      "date": "2026-02-05",
      "clicks": 125,
      "impressions": 75926,
      "ctr": 0.0016463398572294076,
      "position": 33.23543977030266
    },
    {
      "date": "2026-02-06",
      "clicks": 94,
      "impressions": 39329,
      "ctr": 0.002390093823895853,
      "position": 28.146863637519388
    },
    {
      "date": "2026-02-07",
      "clicks": 54,
      "impressions": 29778,
      "ctr": 0.0018134193028410237,
      "position": 26.32906843978776
    },
    {
      "date": "2026-02-08",
      "clicks": 40,
      "impressions": 40944,
      "ctr": 0.0009769441187964048,
      "position": 22.6004054318093
    },
    {
      "date": "2026-02-09",
      "clicks": 114,
      "impressions": 37343,
      "ctr": 0.003052780976354337,
      "position": 23.586937310874863
    },
    {
      "date": "2026-02-10",
      "clicks": 78,
      "impressions": 43405,
      "ctr": 0.001797027992166801,
      "position": 21.223154014514456
    },
    {
      "date": "2026-02-11",
      "clicks": 110,
      "impressions": 36259,
      "ctr": 0.003033729556799691,
      "position": 26.72401334841005
    },
    {
      "date": "2026-02-12",
      "clicks": 91,
      "impressions": 31937,
      "ctr": 0.0028493596768638255,
      "position": 26.049973385101918
    },
    {
      "date": "2026-02-13",
      "clicks": 90,
      "impressions": 24383,
      "ctr": 0.00369109625558791,
      "position": 22.102612475905342
    },
    {
      "date": "2026-02-14",
      "clicks": 31,
      "impressions": 23366,
      "ctr": 0.0013267140289309253,
      "position": 23.900924420097578
    },
    {
      "date": "2026-02-15",
      "clicks": 45,
      "impressions": 28136,
      "ctr": 0.0015993744668751776,
      "position": 23.33167472277509
    },
    {
      "date": "2026-02-16",
      "clicks": 78,
      "impressions": 32579,
      "ctr": 0.002394180300193376,
      "position": 18.65757082783388
    },
    {
      "date": "2026-02-17",
      "clicks": 96,
      "impressions": 33302,
      "ctr": 0.0028827097471623327,
      "position": 20.610714071226955
    },
    {
      "date": "2026-02-18",
      "clicks": 101,
      "impressions": 33051,
      "ctr": 0.00305588333182052,
      "position": 24.124201990862606
    },
    {
      "date": "2026-02-19",
      "clicks": 77,
      "impressions": 30735,
      "ctr": 0.002505287131934277,
      "position": 19.658662762323086
    },
    {
      "date": "2026-02-20",
      "clicks": 67,
      "impressions": 28724,
      "ctr": 0.002332544213897786,
      "position": 20.645731792229494
    },
    {
      "date": "2026-02-21",
      "clicks": 47,
      "impressions": 29580,
      "ctr": 0.0015889114266396213,
      "position": 22.37183908045977
    },
    {
      "date": "2026-02-22",
      "clicks": 33,
      "impressions": 31727,
      "ctr": 0.0010401235540706654,
      "position": 19.516437104043874
    },
    {
      "date": "2026-02-23",
      "clicks": 99,
      "impressions": 53821,
      "ctr": 0.001839430705486706,
      "position": 12.787685104327307
    },
    {
      "date": "2026-02-24",
      "clicks": 106,
      "impressions": 29845,
      "ctr": 0.003551683699112079,
      "position": 19.830792427542303
    },
    {
      "date": "2026-02-25",
      "clicks": 126,
      "impressions": 34034,
      "ctr": 0.003702180172768408,
      "position": 22.672033848504437
    },
    {
      "date": "2026-02-26",
      "clicks": 91,
      "impressions": 30332,
      "ctr": 0.0030001318739285242,
      "position": 19.484175128577082
    },
    {
      "date": "2026-02-27",
      "clicks": 75,
      "impressions": 31369,
      "ctr": 0.0023908954700500493,
      "position": 20.69578246039083
    },
    {
      "date": "2026-02-28",
      "clicks": 30,
      "impressions": 30900,
      "ctr": 0.000970873786407767,
      "position": 20.58546925566343
    },
    {
      "date": "2026-03-01",
      "clicks": 45,
      "impressions": 32655,
      "ctr": 0.0013780431786862655,
      "position": 23.055887306691165
    },
    {
      "date": "2026-03-02",
      "clicks": 105,
      "impressions": 48093,
      "ctr": 0.0021832699145405777,
      "position": 15.635809785207826
    },
    {
      "date": "2026-03-03",
      "clicks": 103,
      "impressions": 65809,
      "ctr": 0.001565135467793159,
      "position": 10.740704159005608
    },
    {
      "date": "2026-03-04",
      "clicks": 104,
      "impressions": 32666,
      "ctr": 0.003183738443641707,
      "position": 20.478264862548215
    },
    {
      "date": "2026-03-05",
      "clicks": 89,
      "impressions": 34363,
      "ctr": 0.0025899950528184383,
      "position": 14.747140820068097
    },
    {
      "date": "2026-03-06",
      "clicks": 96,
      "impressions": 25165,
      "ctr": 0.0038148221736538845,
      "position": 18.111504073117423
    },
    {
      "date": "2026-03-07",
      "clicks": 48,
      "impressions": 22914,
      "ctr": 0.002094789211835559,
      "position": 18.60857990748014
    },
    {
      "date": "2026-03-08",
      "clicks": 40,
      "impressions": 23464,
      "ctr": 0.0017047391749062393,
      "position": 18.595508012274124
    },
    {
      "date": "2026-03-09",
      "clicks": 93,
      "impressions": 30774,
      "ctr": 0.003022031585104309,
      "position": 17.969617209332554
    },
    {
      "date": "2026-03-10",
      "clicks": 84,
      "impressions": 35147,
      "ctr": 0.0023899621589324837,
      "position": 15.019432668506559
    },
    {
      "date": "2026-03-11",
      "clicks": 98,
      "impressions": 31188,
      "ctr": 0.0031422341926381943,
      "position": 19.229639604976274
    },
    {
      "date": "2026-03-12",
      "clicks": 115,
      "impressions": 33951,
      "ctr": 0.0033872345439015052,
      "position": 18.382374598686344
    },
    {
      "date": "2026-03-13",
      "clicks": 68,
      "impressions": 30891,
      "ctr": 0.0022012884011524394,
      "position": 21.689132757113722
    },
    {
      "date": "2026-03-14",
      "clicks": 39,
      "impressions": 28099,
      "ctr": 0.0013879497491013915,
      "position": 22.14488060073312
    },
    {
      "date": "2026-03-15",
      "clicks": 35,
      "impressions": 29289,
      "ctr": 0.0011949878794086518,
      "position": 22.959233842056744
    },
    {
      "date": "2026-03-16",
      "clicks": 91,
      "impressions": 60229,
      "ctr": 0.00151090006475286,
      "position": 13.635673844825583
    },
    {
      "date": "2026-03-17",
      "clicks": 89,
      "impressions": 36139,
      "ctr": 0.002462713412103268,
      "position": 19.28019591023548
    },
    {
      "date": "2026-03-18",
      "clicks": 97,
      "impressions": 30876,
      "ctr": 0.003141598652675217,
      "position": 21.398723927969943
    },
    {
      "date": "2026-03-19",
      "clicks": 76,
      "impressions": 30195,
      "ctr": 0.0025169730087762875,
      "position": 20.546315615168073
    },
    {
      "date": "2026-03-20",
      "clicks": 94,
      "impressions": 25829,
      "ctr": 0.003639320144024159,
      "position": 21.682837121065468
    },
    {
      "date": "2026-03-21",
      "clicks": 45,
      "impressions": 28899,
      "ctr": 0.0015571473061351605,
      "position": 22.192774836499535
    },
    {
      "date": "2026-03-22",
      "clicks": 39,
      "impressions": 24973,
      "ctr": 0.0015616866215512754,
      "position": 21.099387338325393
    },
    {
      "date": "2026-03-23",
      "clicks": 114,
      "impressions": 33478,
      "ctr": 0.00340522133938706,
      "position": 17.920514965051677
    },
    {
      "date": "2026-03-24",
      "clicks": 99,
      "impressions": 32089,
      "ctr": 0.0030851693726822275,
      "position": 18.431518588924554
    },
    {
      "date": "2026-03-25",
      "clicks": 113,
      "impressions": 31688,
      "ctr": 0.003566018682150972,
      "position": 20.250189346124717
    },
    {
      "date": "2026-03-26",
      "clicks": 106,
      "impressions": 34232,
      "ctr": 0.0030965178780088805,
      "position": 22.366791306379994
    },
    {
      "date": "2026-03-27",
      "clicks": 77,
      "impressions": 33546,
      "ctr": 0.0022953556310737495,
      "position": 17.565283491325346
    },
    {
      "date": "2026-03-28",
      "clicks": 37,
      "impressions": 29811,
      "ctr": 0.0012411525946798162,
      "position": 19.85874341685955
    },
    {
      "date": "2026-03-29",
      "clicks": 36,
      "impressions": 27448,
      "ctr": 0.0013115709705625181,
      "position": 19.9779218886622
    },
    {
      "date": "2026-03-30",
      "clicks": 103,
      "impressions": 33263,
      "ctr": 0.003096533686077624,
      "position": 17.350810209542132
    },
    {
      "date": "2026-03-31",
      "clicks": 93,
      "impressions": 29648,
      "ctr": 0.0031368051807879114,
      "position": 15.932980302212629
    },
    {
      "date": "2026-04-01",
      "clicks": 90,
      "impressions": 32213,
      "ctr": 0.0027939030826064012,
      "position": 17.827647223170768
    },
    {
      "date": "2026-04-02",
      "clicks": 90,
      "impressions": 24915,
      "ctr": 0.003612281757977122,
      "position": 17.49383905277945
    },
    {
      "date": "2026-04-03",
      "clicks": 48,
      "impressions": 22667,
      "ctr": 0.002117615917412979,
      "position": 20.50941897913266
    },
    {
      "date": "2026-04-04",
      "clicks": 49,
      "impressions": 20783,
      "ctr": 0.0023576961940047153,
      "position": 19.460376269066064
    }
  ],
  "topQueries": [
    {
      "query": "kogan and disalvo",
      "clicks": 714,
      "impressions": 2168,
      "ctr": 0.32933579335793356,
      "position": 1.3574723247232472
    },
    {
      "query": "kogan & disalvo",
      "clicks": 276,
      "impressions": 576,
      "ctr": 0.4791666666666667,
      "position": 1.4322916666666667
    },
    {
      "query": "laurie rabyor",
      "clicks": 162,
      "impressions": 1534,
      "ctr": 0.10560625814863103,
      "position": 2.8402868318122554
    },
    {
      "query": "kogan disalvo",
      "clicks": 148,
      "impressions": 335,
      "ctr": 0.4417910447761194,
      "position": 2.2388059701492535
    },
    {
      "query": "tampa personal injury lawyer",
      "clicks": 133,
      "impressions": 2065,
      "ctr": 0.06440677966101695,
      "position": 52.751089588377724
    },
    {
      "query": "personal injury attorney delray beach",
      "clicks": 105,
      "impressions": 588,
      "ctr": 0.17857142857142858,
      "position": 14.709183673469388
    },
    {
      "query": "personal injury lawyers boca raton",
      "clicks": 105,
      "impressions": 1217,
      "ctr": 0.08627773212818406,
      "position": 8.921939194741167
    },
    {
      "query": "personal injury lawyers st petersburg florida",
      "clicks": 100,
      "impressions": 786,
      "ctr": 0.1272264631043257,
      "position": 8.993638676844784
    },
    {
      "query": "kogan & disalvo personal injury lawyers",
      "clicks": 84,
      "impressions": 970,
      "ctr": 0.0865979381443299,
      "position": 1.702061855670103
    },
    {
      "query": "personal injury lawyer west palm beach",
      "clicks": 83,
      "impressions": 2818,
      "ctr": 0.029453513129879347,
      "position": 26.362668559261888
    },
    {
      "query": "kogan injury law",
      "clicks": 53,
      "impressions": 113,
      "ctr": 0.4690265486725664,
      "position": 5.68141592920354
    },
    {
      "query": "personal injury lawyer fort lauderdale",
      "clicks": 49,
      "impressions": 1112,
      "ctr": 0.044064748201438846,
      "position": 38.62320143884892
    },
    {
      "query": "kogan & disalvo,p.a.",
      "clicks": 35,
      "impressions": 86,
      "ctr": 0.4069767441860465,
      "position": 1
    },
    {
      "query": "kogan and disalvo boynton beach",
      "clicks": 31,
      "impressions": 207,
      "ctr": 0.1497584541062802,
      "position": 4.1062801932367154
    },
    {
      "query": "kogan and disalvo law firm",
      "clicks": 31,
      "impressions": 95,
      "ctr": 0.3263157894736842,
      "position": 1.431578947368421
    },
    {
      "query": "casey gartland attorney",
      "clicks": 30,
      "impressions": 66,
      "ctr": 0.45454545454545453,
      "position": 1
    },
    {
      "query": "kogan & disalvo, p.a.",
      "clicks": 29,
      "impressions": 61,
      "ctr": 0.47540983606557374,
      "position": 1.0163934426229508
    },
    {
      "query": "casey gartland",
      "clicks": 28,
      "impressions": 112,
      "ctr": 0.25,
      "position": 2.0892857142857144
    },
    {
      "query": "jay london attorney",
      "clicks": 28,
      "impressions": 62,
      "ctr": 0.45161290322580644,
      "position": 1.3225806451612903
    },
    {
      "query": "kogan & disalvo personal injury law",
      "clicks": 27,
      "impressions": 90,
      "ctr": 0.3,
      "position": 1
    },
    {
      "query": "tiffany fanelli",
      "clicks": 23,
      "impressions": 188,
      "ctr": 0.12234042553191489,
      "position": 2.7872340425531914
    },
    {
      "query": "darryl kogan",
      "clicks": 22,
      "impressions": 97,
      "ctr": 0.2268041237113402,
      "position": 5.072164948453608
    },
    {
      "query": "kogan and disalvo stuart",
      "clicks": 21,
      "impressions": 168,
      "ctr": 0.125,
      "position": 4.333333333333334
    },
    {
      "query": "paul silvestri",
      "clicks": 19,
      "impressions": 222,
      "ctr": 0.08558558558558559,
      "position": 4.238738738738739
    },
    {
      "query": "kogan and disalvo boca raton",
      "clicks": 18,
      "impressions": 228,
      "ctr": 0.07894736842105263,
      "position": 5.894736842105263
    },
    {
      "query": "todd baker attorney",
      "clicks": 16,
      "impressions": 65,
      "ctr": 0.24615384615384617,
      "position": 2.3846153846153846
    },
    {
      "query": "darryl kogan attorney",
      "clicks": 13,
      "impressions": 41,
      "ctr": 0.3170731707317073,
      "position": 1
    },
    {
      "query": "todd baker attorney florida",
      "clicks": 12,
      "impressions": 24,
      "ctr": 0.5,
      "position": 1.3333333333333333
    },
    {
      "query": "561-375-9500",
      "clicks": 10,
      "impressions": 77,
      "ctr": 0.12987012987012986,
      "position": 1.0129870129870129
    },
    {
      "query": "kogan and desalvo",
      "clicks": 10,
      "impressions": 34,
      "ctr": 0.29411764705882354,
      "position": 2
    },
    {
      "query": "what happens if someone sues you for more than your insurance covers in florida",
      "clicks": 10,
      "impressions": 126,
      "ctr": 0.07936507936507936,
      "position": 2.7936507936507935
    },
    {
      "query": "kogan and disalvo plantation",
      "clicks": 9,
      "impressions": 49,
      "ctr": 0.1836734693877551,
      "position": 1
    },
    {
      "query": "kogan & disalvo law firm",
      "clicks": 8,
      "impressions": 41,
      "ctr": 0.1951219512195122,
      "position": 1.024390243902439
    },
    {
      "query": "kogan and disalvo reviews",
      "clicks": 7,
      "impressions": 127,
      "ctr": 0.05511811023622047,
      "position": 5.338582677165355
    },
    {
      "query": "disalvo",
      "clicks": 6,
      "impressions": 573,
      "ctr": 0.010471204188481676,
      "position": 9.664921465968586
    },
    {
      "query": "kogan law firm",
      "clicks": 6,
      "impressions": 36,
      "ctr": 0.16666666666666666,
      "position": 5.166666666666667
    },
    {
      "query": "laurie rabyor florida",
      "clicks": 6,
      "impressions": 101,
      "ctr": 0.0594059405940594,
      "position": 3.01980198019802
    },
    {
      "query": "charles bowen attorney",
      "clicks": 5,
      "impressions": 40,
      "ctr": 0.125,
      "position": 5
    },
    {
      "query": "disability lawyers near me",
      "clicks": 5,
      "impressions": 700,
      "ctr": 0.007142857142857143,
      "position": 17.235714285714284
    },
    {
      "query": "how to get traffic camera footage in florida",
      "clicks": 5,
      "impressions": 245,
      "ctr": 0.02040816326530612,
      "position": 3.3918367346938774
    },
    {
      "query": "medical malpractice attorneys",
      "clicks": 5,
      "impressions": 3212,
      "ctr": 0.001556662515566625,
      "position": 21.10180572851806
    },
    {
      "query": "whose insurance pays in a multi car accident",
      "clicks": 5,
      "impressions": 273,
      "ctr": 0.018315018315018316,
      "position": 30.073260073260073
    },
    {
      "query": "boynton beach personal injury lawyer",
      "clicks": 4,
      "impressions": 966,
      "ctr": 0.004140786749482402,
      "position": 10.73913043478261
    },
    {
      "query": "dwayne haskins",
      "clicks": 4,
      "impressions": 606,
      "ctr": 0.006600660066006601,
      "position": 3.17986798679868
    },
    {
      "query": "dwayne haskins accident",
      "clicks": 4,
      "impressions": 263,
      "ctr": 0.015209125475285171,
      "position": 2.6577946768060836
    },
    {
      "query": "mike ryan attorney",
      "clicks": 4,
      "impressions": 33,
      "ctr": 0.12121212121212122,
      "position": 7.303030303030303
    },
    {
      "query": "personal injury attorneys near me",
      "clicks": 4,
      "impressions": 485,
      "ctr": 0.008247422680412371,
      "position": 25.224742268041236
    },
    {
      "query": "suing workers comp",
      "clicks": 4,
      "impressions": 39,
      "ctr": 0.10256410256410256,
      "position": 3.8461538461538463
    },
    {
      "query": "ted disalvo",
      "clicks": 4,
      "impressions": 33,
      "ctr": 0.12121212121212122,
      "position": 2.212121212121212
    },
    {
      "query": "todd baker",
      "clicks": 4,
      "impressions": 87,
      "ctr": 0.04597701149425287,
      "position": 9.67816091954023
    },
    {
      "query": "brigitte jolliet",
      "clicks": 3,
      "impressions": 18,
      "ctr": 0.16666666666666666,
      "position": 1.5
    },
    {
      "query": "can i refuse a recorded statement to insurance company",
      "clicks": 3,
      "impressions": 624,
      "ctr": 0.004807692307692308,
      "position": 4.897435897435898
    },
    {
      "query": "can you sue for more than policy limits in florida",
      "clicks": 3,
      "impressions": 147,
      "ctr": 0.02040816326530612,
      "position": 2.1156462585034013
    },
    {
      "query": "car accident lawyer",
      "clicks": 3,
      "impressions": 13764,
      "ctr": 0.00021795989537925023,
      "position": 11.11878814298169
    },
    {
      "query": "how much of a 30k settlement will i get? tell me about medical liens",
      "clicks": 3,
      "impressions": 35,
      "ctr": 0.08571428571428572,
      "position": 3.5714285714285716
    },
    {
      "query": "is car accident settlement taxable",
      "clicks": 3,
      "impressions": 22,
      "ctr": 0.13636363636363635,
      "position": 32.59090909090909
    },
    {
      "query": "kevin major",
      "clicks": 3,
      "impressions": 13,
      "ctr": 0.23076923076923078,
      "position": 8.461538461538462
    },
    {
      "query": "kogan law",
      "clicks": 3,
      "impressions": 76,
      "ctr": 0.039473684210526314,
      "position": 4.289473684210526
    },
    {
      "query": "mass tort law firms",
      "clicks": 3,
      "impressions": 54,
      "ctr": 0.05555555555555555,
      "position": 43.75925925925926
    },
    {
      "query": "medical malpractice attorneys vero beach",
      "clicks": 3,
      "impressions": 241,
      "ctr": 0.012448132780082987,
      "position": 22.57676348547718
    },
    {
      "query": "slip and fall lawyers",
      "clicks": 3,
      "impressions": 30507,
      "ctr": 0.00009833808634083981,
      "position": 8.368636706329696
    },
    {
      "query": "sonia masters",
      "clicks": 3,
      "impressions": 38,
      "ctr": 0.07894736842105263,
      "position": 3.1578947368421053
    },
    {
      "query": "steven willner",
      "clicks": 3,
      "impressions": 30,
      "ctr": 0.1,
      "position": 3.933333333333333
    },
    {
      "query": "stuart mass",
      "clicks": 3,
      "impressions": 28,
      "ctr": 0.10714285714285714,
      "position": 7.678571428571429
    },
    {
      "query": "yes",
      "clicks": 3,
      "impressions": 68,
      "ctr": 0.04411764705882353,
      "position": 3.985294117647059
    },
    {
      "query": "5613759500",
      "clicks": 2,
      "impressions": 69,
      "ctr": 0.028985507246376812,
      "position": 1.0289855072463767
    },
    {
      "query": "accident attorneys near me",
      "clicks": 2,
      "impressions": 66,
      "ctr": 0.030303030303030304,
      "position": 15.257575757575758
    },
    {
      "query": "accident report",
      "clicks": 2,
      "impressions": 116,
      "ctr": 0.017241379310344827,
      "position": 10.060344827586206
    },
    {
      "query": "boat accident today near me",
      "clicks": 2,
      "impressions": 4,
      "ctr": 0.5,
      "position": 5.25
    },
    {
      "query": "boynton beach medical malpractice lawyer",
      "clicks": 2,
      "impressions": 73,
      "ctr": 0.0273972602739726,
      "position": 5.794520547945205
    },
    {
      "query": "brevard county personal injury attorney",
      "clicks": 2,
      "impressions": 4,
      "ctr": 0.5,
      "position": 6
    },
    {
      "query": "can a 1099 employee get workers comp",
      "clicks": 2,
      "impressions": 9,
      "ctr": 0.2222222222222222,
      "position": 2.111111111111111
    },
    {
      "query": "can at fault driver sue me",
      "clicks": 2,
      "impressions": 53,
      "ctr": 0.03773584905660377,
      "position": 2.566037735849057
    },
    {
      "query": "car accident lawyer boynton beach",
      "clicks": 2,
      "impressions": 1385,
      "ctr": 0.001444043321299639,
      "position": 4.52274368231047
    },
    {
      "query": "catastrophic injury lawsuit",
      "clicks": 2,
      "impressions": 276,
      "ctr": 0.007246376811594203,
      "position": 13.365942028985508
    },
    {
      "query": "charles bowen",
      "clicks": 2,
      "impressions": 68,
      "ctr": 0.029411764705882353,
      "position": 8.25
    },
    {
      "query": "desalvo law firm",
      "clicks": 2,
      "impressions": 59,
      "ctr": 0.03389830508474576,
      "position": 13.64406779661017
    },
    {
      "query": "does progressive pay claims well",
      "clicks": 2,
      "impressions": 149,
      "ctr": 0.013422818791946308,
      "position": 2.530201342281879
    },
    {
      "query": "dwayne haskins car accident",
      "clicks": 2,
      "impressions": 207,
      "ctr": 0.00966183574879227,
      "position": 7.7101449275362315
    },
    {
      "query": "dwayne haskins last words",
      "clicks": 2,
      "impressions": 72,
      "ctr": 0.027777777777777776,
      "position": 2.458333333333333
    },
    {
      "query": "florida crash portal",
      "clicks": 2,
      "impressions": 276,
      "ctr": 0.007246376811594203,
      "position": 9.923913043478262
    },
    {
      "query": "florida motorcycle accident lawyer",
      "clicks": 2,
      "impressions": 3968,
      "ctr": 0.0005040322580645161,
      "position": 4.043346774193548
    },
    {
      "query": "florida personal injury lawyer",
      "clicks": 2,
      "impressions": 4978,
      "ctr": 0.0004017677782241864,
      "position": 12.53274407392527
    },
    {
      "query": "florida personal injury lawyers",
      "clicks": 2,
      "impressions": 6643,
      "ctr": 0.0003010687942194792,
      "position": 6.891163630889658
    },
    {
      "query": "how do i look up an accident report in florida",
      "clicks": 2,
      "impressions": 682,
      "ctr": 0.002932551319648094,
      "position": 2.0425219941348973
    },
    {
      "query": "how much of a $100k settlement will i get? calculate a sample net amount",
      "clicks": 2,
      "impressions": 69,
      "ctr": 0.028985507246376812,
      "position": 3.1594202898550723
    },
    {
      "query": "how to look up an accident report",
      "clicks": 2,
      "impressions": 18,
      "ctr": 0.1111111111111111,
      "position": 7.666666666666667
    },
    {
      "query": "injury lawyer near me",
      "clicks": 2,
      "impressions": 2187,
      "ctr": 0.0009144947416552355,
      "position": 18.039780521262003
    },
    {
      "query": "is a car accident settlement taxable",
      "clicks": 2,
      "impressions": 28,
      "ctr": 0.07142857142857142,
      "position": 34.42857142857143
    },
    {
      "query": "malpractice attorney near me",
      "clicks": 2,
      "impressions": 326,
      "ctr": 0.006134969325153374,
      "position": 11.223926380368098
    },
    {
      "query": "malpractice lawyers",
      "clicks": 2,
      "impressions": 273,
      "ctr": 0.007326007326007326,
      "position": 10.791208791208792
    },
    {
      "query": "michael scott attorney",
      "clicks": 2,
      "impressions": 42,
      "ctr": 0.047619047619047616,
      "position": 7.190476190476191
    },
    {
      "query": "mike ryan lawyer",
      "clicks": 2,
      "impressions": 20,
      "ctr": 0.1,
      "position": 5.6
    },
    {
      "query": "palm beach injury lawyer",
      "clicks": 2,
      "impressions": 42,
      "ctr": 0.047619047619047616,
      "position": 17.38095238095238
    },
    {
      "query": "personal injury attorney near me",
      "clicks": 2,
      "impressions": 4203,
      "ctr": 0.0004758505829169641,
      "position": 8.672852724244589
    },
    {
      "query": "personal injury attorneys",
      "clicks": 2,
      "impressions": 6563,
      "ctr": 0.00030473868657626083,
      "position": 17.645893646198385
    },
    {
      "query": "personal injury lawyers florida",
      "clicks": 2,
      "impressions": 959,
      "ctr": 0.0020855057351407717,
      "position": 15.423357664233576
    },
    {
      "query": "personal injury lawyers tampa",
      "clicks": 2,
      "impressions": 555,
      "ctr": 0.0036036036036036037,
      "position": 46.84504504504505
    },
    {
      "query": "slip and fall lawyer",
      "clicks": 2,
      "impressions": 21615,
      "ctr": 0.00009252833680314597,
      "position": 11.827619708535739
    },
    {
      "query": "social security disability attorney near me",
      "clicks": 2,
      "impressions": 281,
      "ctr": 0.0071174377224199285,
      "position": 24.402135231316727
    },
    {
      "query": "social security disability lawyers",
      "clicks": 2,
      "impressions": 336,
      "ctr": 0.005952380952380952,
      "position": 18.282738095238095
    },
    {
      "query": "social security lawyers",
      "clicks": 2,
      "impressions": 248,
      "ctr": 0.008064516129032258,
      "position": 16.375
    },
    {
      "query": "south florida personal injury attorney",
      "clicks": 2,
      "impressions": 67,
      "ctr": 0.029850746268656716,
      "position": 17.044776119402986
    },
    {
      "query": "south florida personal injury lawyer",
      "clicks": 2,
      "impressions": 378,
      "ctr": 0.005291005291005291,
      "position": 24.85185185185185
    },
    {
      "query": "ssdi lawyers near me",
      "clicks": 2,
      "impressions": 269,
      "ctr": 0.007434944237918215,
      "position": 20.37174721189591
    },
    {
      "query": "what happens if someone else is driving my car and gets in an accident in florida",
      "clicks": 2,
      "impressions": 81,
      "ctr": 0.024691358024691357,
      "position": 7.753086419753086
    },
    {
      "query": "what happens if someone sues you for more than your insurance covers",
      "clicks": 2,
      "impressions": 9,
      "ctr": 0.2222222222222222,
      "position": 6.888888888888889
    },
    {
      "query": "where did dwayne haskins die",
      "clicks": 2,
      "impressions": 54,
      "ctr": 0.037037037037037035,
      "position": 4
    },
    {
      "query": "why is fort lauderdale so dangerous",
      "clicks": 2,
      "impressions": 575,
      "ctr": 0.0034782608695652175,
      "position": 2.4852173913043476
    },
    {
      "query": "workers comp lawyer",
      "clicks": 2,
      "impressions": 1431,
      "ctr": 0.001397624039133473,
      "position": 14.566736547868624
    },
    {
      "query": "3 car accident who pays",
      "clicks": 1,
      "impressions": 28,
      "ctr": 0.03571428571428571,
      "position": 14.142857142857142
    },
    {
      "query": "abogados de accidentes",
      "clicks": 1,
      "impressions": 1219,
      "ctr": 0.0008203445447087777,
      "position": 7.954060705496309
    },
    {
      "query": "abogados para accidente de trabajo",
      "clicks": 1,
      "impressions": 1,
      "ctr": 1,
      "position": 18
    },
    {
      "query": "accident jacksonville fl",
      "clicks": 1,
      "impressions": 2,
      "ctr": 0.5,
      "position": 9
    },
    {
      "query": "accidente en miami hoy",
      "clicks": 1,
      "impressions": 1,
      "ctr": 1,
      "position": 4
    },
    {
      "query": "apply for workers compensation",
      "clicks": 1,
      "impressions": 14,
      "ctr": 0.07142857142857142,
      "position": 3.5
    },
    {
      "query": "are 1099 employees covered by workers comp",
      "clicks": 1,
      "impressions": 160,
      "ctr": 0.00625,
      "position": 24.3625
    },
    {
      "query": "are auto accident settlements taxable",
      "clicks": 1,
      "impressions": 18,
      "ctr": 0.05555555555555555,
      "position": 10.166666666666666
    },
    {
      "query": "are car accident settlements taxable",
      "clicks": 1,
      "impressions": 91,
      "ctr": 0.01098901098901099,
      "position": 28.043956043956044
    },
    {
      "query": "are personal injury settlements taxable in florida",
      "clicks": 1,
      "impressions": 15,
      "ctr": 0.06666666666666667,
      "position": 15.8
    },
    {
      "query": "at fault accident florida",
      "clicks": 1,
      "impressions": 5,
      "ctr": 0.2,
      "position": 68
    },
    {
      "query": "at fault accident lawyer near me",
      "clicks": 1,
      "impressions": 1,
      "ctr": 1,
      "position": 13
    },
    {
      "query": "at fault driver suing me",
      "clicks": 1,
      "impressions": 26,
      "ctr": 0.038461538461538464,
      "position": 6.3076923076923075
    },
    {
      "query": "attorney boynton beach",
      "clicks": 1,
      "impressions": 11,
      "ctr": 0.09090909090909091,
      "position": 3.3636363636363638
    },
    {
      "query": "attorney for social security",
      "clicks": 1,
      "impressions": 51,
      "ctr": 0.0196078431372549,
      "position": 22.823529411764707
    },
    {
      "query": "attorney near me",
      "clicks": 1,
      "impressions": 11,
      "ctr": 0.09090909090909091,
      "position": 3.5454545454545454
    },
    {
      "query": "attorney social security disability",
      "clicks": 1,
      "impressions": 59,
      "ctr": 0.01694915254237288,
      "position": 57.69491525423729
    },
    {
      "query": "auto accident attorney",
      "clicks": 1,
      "impressions": 3708,
      "ctr": 0.00026968716289104636,
      "position": 15.783171521035598
    },
    {
      "query": "automotive product liability lawyer",
      "clicks": 1,
      "impressions": 1,
      "ctr": 1,
      "position": 1
    },
    {
      "query": "best attorneys for medical malpractice",
      "clicks": 1,
      "impressions": 76,
      "ctr": 0.013157894736842105,
      "position": 51.48684210526316
    },
    {
      "query": "best dental malpractice lawyers near me",
      "clicks": 1,
      "impressions": 7,
      "ctr": 0.14285714285714285,
      "position": 5.428571428571429
    },
    {
      "query": "best disability attorney near me",
      "clicks": 1,
      "impressions": 186,
      "ctr": 0.005376344086021506,
      "position": 39.204301075268816
    },
    {
      "query": "best injury attorneys",
      "clicks": 1,
      "impressions": 4,
      "ctr": 0.25,
      "position": 11.5
    },
    {
      "query": "best personal injury lawyer fort lauderdale",
      "clicks": 1,
      "impressions": 33,
      "ctr": 0.030303030303030304,
      "position": 32.39393939393939
    },
    {
      "query": "best personal injury lawyer west palm beach",
      "clicks": 1,
      "impressions": 8,
      "ctr": 0.125,
      "position": 1
    },
    {
      "query": "best ssi disability lawyers near me",
      "clicks": 1,
      "impressions": 2,
      "ctr": 0.5,
      "position": 11.5
    },
    {
      "query": "best workers comp lawyers in florida",
      "clicks": 1,
      "impressions": 46,
      "ctr": 0.021739130434782608,
      "position": 14.847826086956522
    },
    {
      "query": "best workers' comp lawyers in florida",
      "clicks": 1,
      "impressions": 36,
      "ctr": 0.027777777777777776,
      "position": 14.63888888888889
    },
    {
      "query": "big law firms near me",
      "clicks": 1,
      "impressions": 2,
      "ctr": 0.5,
      "position": 1
    },
    {
      "query": "boat accident palm beach",
      "clicks": 1,
      "impressions": 27,
      "ctr": 0.037037037037037035,
      "position": 8.37037037037037
    },
    {
      "query": "bobby hurley accident",
      "clicks": 1,
      "impressions": 1,
      "ctr": 1,
      "position": 3
    },
    {
      "query": "boca raton car accident lawyer near me",
      "clicks": 1,
      "impressions": 7,
      "ctr": 0.14285714285714285,
      "position": 37.42857142857143
    },
    {
      "query": "boca raton car accident lawyers",
      "clicks": 1,
      "impressions": 168,
      "ctr": 0.005952380952380952,
      "position": 35.773809523809526
    },
    {
      "query": "boca raton personal injury lawyer",
      "clicks": 1,
      "impressions": 2732,
      "ctr": 0.00036603221083455345,
      "position": 23.199121522693996
    },
    {
      "query": "boca raton slip and fall lawyer",
      "clicks": 1,
      "impressions": 2412,
      "ctr": 0.00041459369817578774,
      "position": 15.041873963515755
    },
    {
      "query": "boynton beach bicycle accident lawyer",
      "clicks": 1,
      "impressions": 331,
      "ctr": 0.0030211480362537764,
      "position": 10.283987915407854
    },
    {
      "query": "boynton beach drunk driving accident lawyer",
      "clicks": 1,
      "impressions": 14,
      "ctr": 0.07142857142857142,
      "position": 15.428571428571429
    },
    {
      "query": "boynton beach motorcycle accident lawyer",
      "clicks": 1,
      "impressions": 547,
      "ctr": 0.0018281535648994515,
      "position": 11.352833638025594
    },
    {
      "query": "boynton beach pedestrian accident lawyer",
      "clicks": 1,
      "impressions": 164,
      "ctr": 0.006097560975609756,
      "position": 5.591463414634147
    },
    {
      "query": "boynton beach premises liability lawyer",
      "clicks": 1,
      "impressions": 16,
      "ctr": 0.0625,
      "position": 34.4375
    },
    {
      "query": "boynton beach swimming pool accident lawyer",
      "clicks": 1,
      "impressions": 18,
      "ctr": 0.05555555555555555,
      "position": 21.444444444444443
    },
    {
      "query": "boynton beach uber accident lawyer",
      "clicks": 1,
      "impressions": 96,
      "ctr": 0.010416666666666666,
      "position": 13.916666666666666
    },
    {
      "query": "boynton beach workers compensation lawyer",
      "clicks": 1,
      "impressions": 166,
      "ctr": 0.006024096385542169,
      "position": 12.024096385542169
    },
    {
      "query": "boynton beach wrongful death lawyer",
      "clicks": 1,
      "impressions": 668,
      "ctr": 0.0014970059880239522,
      "position": 19.934131736526947
    },
    {
      "query": "bubby brewster",
      "clicks": 1,
      "impressions": 1,
      "ctr": 1,
      "position": 3
    },
    {
      "query": "caleb williams stats",
      "clicks": 1,
      "impressions": 1,
      "ctr": 1,
      "position": 4
    },
    {
      "query": "can i sue workers comp insurance company",
      "clicks": 1,
      "impressions": 8,
      "ctr": 0.125,
      "position": 7.25
    },
    {
      "query": "can someone drive my car if they are not on my insurance in florida",
      "clicks": 1,
      "impressions": 20,
      "ctr": 0.05,
      "position": 13.45
    },
    {
      "query": "can you request traffic camera footage",
      "clicks": 1,
      "impressions": 16,
      "ctr": 0.0625,
      "position": 1
    },
    {
      "query": "car accident attorney",
      "clicks": 1,
      "impressions": 8210,
      "ctr": 0.0001218026796589525,
      "position": 12.430572472594397
    },
    {
      "query": "car accident attorney broward county",
      "clicks": 1,
      "impressions": 18,
      "ctr": 0.05555555555555555,
      "position": 17.833333333333332
    },
    {
      "query": "car accident attorney florida",
      "clicks": 1,
      "impressions": 903,
      "ctr": 0.0011074197120708748,
      "position": 31.430786267995572
    },
    {
      "query": "car accident car total loss",
      "clicks": 1,
      "impressions": 1,
      "ctr": 1,
      "position": 5
    },
    {
      "query": "car accident lawyer in boca raton",
      "clicks": 1,
      "impressions": 427,
      "ctr": 0.00234192037470726,
      "position": 35.477751756440284
    },
    {
      "query": "car accident lawyer in orlando",
      "clicks": 1,
      "impressions": 9,
      "ctr": 0.1111111111111111,
      "position": 94.44444444444444
    },
    {
      "query": "car accident lawyer in tampa",
      "clicks": 1,
      "impressions": 176,
      "ctr": 0.005681818181818182,
      "position": 73.2784090909091
    },
    {
      "query": "car accident lawyer plantation",
      "clicks": 1,
      "impressions": 595,
      "ctr": 0.0016806722689075631,
      "position": 12.418487394957983
    },
    {
      "query": "car accident settlement taxable",
      "clicks": 1,
      "impressions": 11,
      "ctr": 0.09090909090909091,
      "position": 3.909090909090909
    },
    {
      "query": "car insurance beacon",
      "clicks": 1,
      "impressions": 44,
      "ctr": 0.022727272727272728,
      "position": 3.5
    },
    {
      "query": "catastrophic injury lawyer florida",
      "clicks": 1,
      "impressions": 242,
      "ctr": 0.004132231404958678,
      "position": 19.93801652892562
    },
    {
      "query": "certified civil trial attorney",
      "clicks": 1,
      "impressions": 4,
      "ctr": 0.25,
      "position": 5.5
    },
    {
      "query": "chinese drywall lawsuit",
      "clicks": 1,
      "impressions": 15,
      "ctr": 0.06666666666666667,
      "position": 13.4
    },
    {
      "query": "civil attorney near me",
      "clicks": 1,
      "impressions": 1,
      "ctr": 1,
      "position": 61
    },
    {
      "query": "coach haskins",
      "clicks": 1,
      "impressions": 4,
      "ctr": 0.25,
      "position": 3
    },
    {
      "query": "cogan law firm",
      "clicks": 1,
      "impressions": 5,
      "ctr": 0.2,
      "position": 3.4
    },
    {
      "query": "crash information",
      "clicks": 1,
      "impressions": 1,
      "ctr": 1,
      "position": 11
    },
    {
      "query": "crash number lookup",
      "clicks": 1,
      "impressions": 28,
      "ctr": 0.03571428571428571,
      "position": 5.107142857142857
    },
    {
      "query": "crash records",
      "clicks": 1,
      "impressions": 25,
      "ctr": 0.04,
      "position": 11.12
    },
    {
      "query": "crash report florida",
      "clicks": 1,
      "impressions": 81,
      "ctr": 0.012345679012345678,
      "position": 14.407407407407407
    },
    {
      "query": "crash reports florida",
      "clicks": 1,
      "impressions": 3,
      "ctr": 0.3333333333333333,
      "position": 12.666666666666666
    },
    {
      "query": "daniel collins lawyer",
      "clicks": 1,
      "impressions": 4,
      "ctr": 0.25,
      "position": 8
    },
    {
      "query": "delayed diagnosis lawsuit",
      "clicks": 1,
      "impressions": 328,
      "ctr": 0.003048780487804878,
      "position": 4.170731707317073
    },
    {
      "query": "dental malpractice lawyer near me",
      "clicks": 1,
      "impressions": 26,
      "ctr": 0.038461538461538464,
      "position": 8.76923076923077
    },
    {
      "query": "disability attorney near me",
      "clicks": 1,
      "impressions": 445,
      "ctr": 0.0022471910112359553,
      "position": 19.55505617977528
    },
    {
      "query": "disability lawyers near me free consultation",
      "clicks": 1,
      "impressions": 7,
      "ctr": 0.14285714285714285,
      "position": 5.857142857142857
    },
    {
      "query": "disablity lawyer",
      "clicks": 1,
      "impressions": 1,
      "ctr": 1,
      "position": 6
    },
    {
      "query": "do 1099 employees need workers' comp in florida",
      "clicks": 1,
      "impressions": 152,
      "ctr": 0.006578947368421052,
      "position": 7.3618421052631575
    },
    {
      "query": "do car accident settlements get taxed",
      "clicks": 1,
      "impressions": 14,
      "ctr": 0.07142857142857142,
      "position": 2.857142857142857
    },
    {
      "query": "do i have to pay taxes on a car accident settlement",
      "clicks": 1,
      "impressions": 18,
      "ctr": 0.05555555555555555,
      "position": 2.2222222222222223
    },
    {
      "query": "do i need a police report if i hit a tree",
      "clicks": 1,
      "impressions": 2,
      "ctr": 0.5,
      "position": 1
    },
    {
      "query": "do you have to have a police report for an accident",
      "clicks": 1,
      "impressions": 6,
      "ctr": 0.16666666666666666,
      "position": 3.3333333333333335
    },
    {
      "query": "do you have to pay taxes on a car accident settlement",
      "clicks": 1,
      "impressions": 19,
      "ctr": 0.05263157894736842,
      "position": 1.368421052631579
    },
    {
      "query": "do you have to pay taxes on car accident settlement",
      "clicks": 1,
      "impressions": 19,
      "ctr": 0.05263157894736842,
      "position": 8.473684210526315
    },
    {
      "query": "do you have to pay taxes on car insurance settlements",
      "clicks": 1,
      "impressions": 5,
      "ctr": 0.2,
      "position": 19.6
    },
    {
      "query": "do you pay taxes on car accident settlement",
      "clicks": 1,
      "impressions": 26,
      "ctr": 0.038461538461538464,
      "position": 1.9615384615384617
    },
    {
      "query": "doctor mistake lawyer",
      "clicks": 1,
      "impressions": 36,
      "ctr": 0.027777777777777776,
      "position": 74.41666666666667
    },
    {
      "query": "does a car accident settlement count as income",
      "clicks": 1,
      "impressions": 5,
      "ctr": 0.2,
      "position": 3.2
    },
    {
      "query": "does health insurance pay for car accident injuries",
      "clicks": 1,
      "impressions": 2,
      "ctr": 0.5,
      "position": 5.5
    },
    {
      "query": "doug martin",
      "clicks": 1,
      "impressions": 1,
      "ctr": 1,
      "position": 3
    },
    {
      "query": "dwanye haskins",
      "clicks": 1,
      "impressions": 5,
      "ctr": 0.2,
      "position": 2.8
    }
  ],
  "topPages": [
    {
      "page": "https://www.kogan-disalvo.com/",
      "clicks": 1467,
      "impressions": 188276,
      "ctr": 0.007791752533514627,
      "position": 22.2141536892647
    },
    {
      "page": "https://www.kogan-disalvo.com/our-attorneys/",
      "clicks": 243,
      "impressions": 30884,
      "ctr": 0.007868151793809092,
      "position": 32.953114881492034
    },
    {
      "page": "https://www.kogan-disalvo.com/firm-news/boynton-beach-driver-saved-by-good-samaritans/",
      "clicks": 212,
      "impressions": 2599,
      "ctr": 0.08156983455175067,
      "position": 4.093882262408618
    },
    {
      "page": "https://www.kogan-disalvo.com/florida-car-accident-lawyer/how-do-i-look-up-an-accident-report-in-florida/",
      "clicks": 196,
      "impressions": 46962,
      "ctr": 0.004173587155572591,
      "position": 6.067863378902091
    },
    {
      "page": "https://www.kogan-disalvo.com/boynton-beach-injury/?utm_source=gmblisting&utm_medium=organic&utm_campaign=Boynton_Beach",
      "clicks": 187,
      "impressions": 66345,
      "ctr": 0.00281859974376366,
      "position": 2.9109654080940537
    },
    {
      "page": "https://www.kogan-disalvo.com/tampa-injury/",
      "clicks": 133,
      "impressions": 47749,
      "ctr": 0.0027853986470920858,
      "position": 41.05761377201617
    },
    {
      "page": "https://www.kogan-disalvo.com/our-attorneys/todd-baker/",
      "clicks": 123,
      "impressions": 1859,
      "ctr": 0.06616460462614308,
      "position": 16.318988703604088
    },
    {
      "page": "https://www.kogan-disalvo.com/west-palm-beach-injury/",
      "clicks": 116,
      "impressions": 104245,
      "ctr": 0.0011127632020720417,
      "position": 21.87127440164996
    },
    {
      "page": "https://www.kogan-disalvo.com/boca-raton-injury/",
      "clicks": 112,
      "impressions": 65284,
      "ctr": 0.001715581153115618,
      "position": 22.826328043624777
    },
    {
      "page": "https://www.kogan-disalvo.com/florida-car-accident-lawyer/are-car-accident-settlements-taxable-in-florida/",
      "clicks": 108,
      "impressions": 6415,
      "ctr": 0.016835541699142635,
      "position": 9.313795791114575
    },
    {
      "page": "https://www.kogan-disalvo.com/contact-us/",
      "clicks": 106,
      "impressions": 11431,
      "ctr": 0.009273029481235238,
      "position": 8.509229288776135
    },
    {
      "page": "https://www.kogan-disalvo.com/delray-beach-injury/",
      "clicks": 101,
      "impressions": 9191,
      "ctr": 0.01098901098901099,
      "position": 25.75976498748776
    },
    {
      "page": "https://www.kogan-disalvo.com/st-petersburg-injury/",
      "clicks": 99,
      "impressions": 13055,
      "ctr": 0.007583301417081578,
      "position": 43.06242818843355
    },
    {
      "page": "https://www.kogan-disalvo.com/our-attorneys/darryl-b-kogan/",
      "clicks": 98,
      "impressions": 3189,
      "ctr": 0.03073063656318595,
      "position": 8.866729382251489
    },
    {
      "page": "https://www.kogan-disalvo.com/our-attorneys/casey-gartland/",
      "clicks": 94,
      "impressions": 1779,
      "ctr": 0.05283867341202923,
      "position": 18.753794266441822
    },
    {
      "page": "https://www.kogan-disalvo.com/florida-car-accident-lawyer/are-parents-liable-for-the-childrens-car-accidents-in-florida/",
      "clicks": 93,
      "impressions": 8032,
      "ctr": 0.011578685258964144,
      "position": 5.929158366533865
    },
    {
      "page": "https://www.kogan-disalvo.com/florida-workers-compensation-lawyer/can-you-sue-if-you-accept-workers-compensation-in-florida/",
      "clicks": 88,
      "impressions": 4216,
      "ctr": 0.020872865275142316,
      "position": 8.121442125237191
    },
    {
      "page": "https://www.kogan-disalvo.com/personal-injury/what-is-a-notice-of-claim-and-when-do-you-need-to-file-one-in-florida/",
      "clicks": 84,
      "impressions": 4587,
      "ctr": 0.01831262262916939,
      "position": 6.147155003270111
    },
    {
      "page": "https://www.kogan-disalvo.com/firm-news/steelers-qb-dwayne-haskins-killed-by-truck-on-florida-highway/",
      "clicks": 83,
      "impressions": 16475,
      "ctr": 0.005037936267071321,
      "position": 4.340333839150228
    },
    {
      "page": "https://www.kogan-disalvo.com/stuart-injury/?utm_source=gmblisting&utm_medium=organic&utm_campaign=Stuart",
      "clicks": 80,
      "impressions": 63571,
      "ctr": 0.00125843545012663,
      "position": 2.199100218653159
    },
    {
      "page": "https://www.kogan-disalvo.com/our-attorneys/jay-s-london/",
      "clicks": 77,
      "impressions": 2315,
      "ctr": 0.03326133909287257,
      "position": 17.673002159827213
    },
    {
      "page": "https://www.kogan-disalvo.com/florida-car-accident-lawyer/what-if-my-florida-auto-accident-settlement-exceeds-my-policy-limits/",
      "clicks": 75,
      "impressions": 5393,
      "ctr": 0.01390691637307621,
      "position": 5.701650287409605
    },
    {
      "page": "https://www.kogan-disalvo.com/our-attorneys/michael-j-ryan/",
      "clicks": 75,
      "impressions": 1665,
      "ctr": 0.04504504504504504,
      "position": 10.276276276276276
    },
    {
      "page": "https://www.kogan-disalvo.com/florida-car-accident-lawyer/can-i-request-traffic-camera-footage-in-florida-after-a-car-accident/",
      "clicks": 72,
      "impressions": 4788,
      "ctr": 0.015037593984962405,
      "position": 5.091687552213868
    },
    {
      "page": "https://www.kogan-disalvo.com/our-attorneys/paul-m-silvestri/",
      "clicks": 72,
      "impressions": 1089,
      "ctr": 0.06611570247933884,
      "position": 10.395775941230486
    },
    {
      "page": "https://www.kogan-disalvo.com/boca-raton-injury/?utm_source=gmblisting&utm_medium=organic&utm_campaign=Boca_Raton",
      "clicks": 67,
      "impressions": 24281,
      "ctr": 0.002759359169721181,
      "position": 7.010955067748445
    },
    {
      "page": "https://www.kogan-disalvo.com/our-attorneys/tiffany-m-fanelli/",
      "clicks": 62,
      "impressions": 1108,
      "ctr": 0.05595667870036101,
      "position": 8.48826714801444
    },
    {
      "page": "https://www.kogan-disalvo.com/our-attorneys/michael-scott/",
      "clicks": 61,
      "impressions": 1686,
      "ctr": 0.036180308422301306,
      "position": 12.729537366548042
    },
    {
      "page": "https://www.kogan-disalvo.com/fort-lauderdale-injury/",
      "clicks": 53,
      "impressions": 55112,
      "ctr": 0.0009616780374510089,
      "position": 33.31250907243432
    },
    {
      "page": "https://www.kogan-disalvo.com/our-attorneys/kevin-major-jr/",
      "clicks": 52,
      "impressions": 487,
      "ctr": 0.10677618069815195,
      "position": 11.004106776180699
    },
    {
      "page": "https://www.kogan-disalvo.com/fort-myers-injury/",
      "clicks": 51,
      "impressions": 58859,
      "ctr": 0.0008664775140590224,
      "position": 22.56239487588984
    },
    {
      "page": "https://www.kogan-disalvo.com/boynton-beach-injury/",
      "clicks": 45,
      "impressions": 28043,
      "ctr": 0.0016046785294012765,
      "position": 20.820454302321433
    },
    {
      "page": "https://www.kogan-disalvo.com/florida-car-accident-lawyer/whose-insurance-pays-in-a-multi-car-accident-in-florida/",
      "clicks": 44,
      "impressions": 3862,
      "ctr": 0.011393060590367685,
      "position": 24.079751424132574
    },
    {
      "page": "https://www.kogan-disalvo.com/st-petersburg-injury/?utm_source=GMBlisting&utm_medium=organic&utm_campaign=St_Pete",
      "clicks": 43,
      "impressions": 31267,
      "ctr": 0.0013752518629865354,
      "position": 5.760162471615441
    },
    {
      "page": "https://www.kogan-disalvo.com/boat-accident/boat-crash-west-palm-beach/",
      "clicks": 42,
      "impressions": 1741,
      "ctr": 0.024124066628374498,
      "position": 14.48879954049397
    },
    {
      "page": "https://www.kogan-disalvo.com/florida-car-accident-lawyer/my-own-insurance-company-wants-a-recorded-statement-what-should-i-do/",
      "clicks": 41,
      "impressions": 5071,
      "ctr": 0.008085190297771643,
      "position": 10.737724314730823
    },
    {
      "page": "https://www.kogan-disalvo.com/our-attorneys/brian-m-andino/",
      "clicks": 41,
      "impressions": 953,
      "ctr": 0.04302203567681007,
      "position": 13.368310598111227
    },
    {
      "page": "https://www.kogan-disalvo.com/plantation-injury/?utm_source=gmblisting&utm_medium=organic&utm_campaign=Fort_Laud",
      "clicks": 41,
      "impressions": 38936,
      "ctr": 0.001053010067803575,
      "position": 2.7680039038422026
    },
    {
      "page": "https://www.kogan-disalvo.com/our-attorneys/alec-zavell/",
      "clicks": 38,
      "impressions": 374,
      "ctr": 0.10160427807486631,
      "position": 15.01336898395722
    },
    {
      "page": "https://www.kogan-disalvo.com/florida-workers-compensation-lawyer/can-an-independent-contractor-receive-workers-compensation-in-florida/",
      "clicks": 37,
      "impressions": 8132,
      "ctr": 0.00454992621741269,
      "position": 13.03787506148549
    },
    {
      "page": "https://www.kogan-disalvo.com/personal-injury/how-a-medical-lien-affects-your-personal-injury-settlement/",
      "clicks": 37,
      "impressions": 6863,
      "ctr": 0.0053912283258050414,
      "position": 8.188255864782164
    },
    {
      "page": "https://www.kogan-disalvo.com/florida-car-accident-lawyer/what-if-my-car-is-totaled-in-an-accident-in-florida/",
      "clicks": 35,
      "impressions": 13331,
      "ctr": 0.002625459455404696,
      "position": 16.535668742029856
    },
    {
      "page": "https://www.kogan-disalvo.com/our-attorneys/sonia-masters/",
      "clicks": 35,
      "impressions": 767,
      "ctr": 0.04563233376792699,
      "position": 18.11864406779661
    },
    {
      "page": "https://www.kogan-disalvo.com/our-attorneys/brigitte-jolliet/",
      "clicks": 34,
      "impressions": 617,
      "ctr": 0.055105348460291734,
      "position": 9.07779578606159
    },
    {
      "page": "https://www.kogan-disalvo.com/our-attorneys/charles-a-bowen-jr/",
      "clicks": 34,
      "impressions": 1249,
      "ctr": 0.02722177742193755,
      "position": 19.028823058446758
    },
    {
      "page": "https://www.kogan-disalvo.com/our-attorneys/rachel-r-schrager/",
      "clicks": 34,
      "impressions": 614,
      "ctr": 0.05537459283387622,
      "position": 12.607491856677525
    },
    {
      "page": "https://www.kogan-disalvo.com/our-attorneys/steven-m-willner/",
      "clicks": 33,
      "impressions": 620,
      "ctr": 0.0532258064516129,
      "position": 12.254838709677419
    },
    {
      "page": "https://www.kogan-disalvo.com/our-attorneys/theodore-l-disalvo/",
      "clicks": 33,
      "impressions": 2790,
      "ctr": 0.011827956989247311,
      "position": 9.416487455197133
    },
    {
      "page": "https://www.kogan-disalvo.com/tampa-injury/?utm_source=GMBlisting&utm_medium=organic&utm_campaign=Tampa",
      "clicks": 33,
      "impressions": 4200,
      "ctr": 0.007857142857142858,
      "position": 21.045
    },
    {
      "page": "https://www.kogan-disalvo.com/dealing-with-auto-insurance/progressive/",
      "clicks": 32,
      "impressions": 5978,
      "ctr": 0.005352960856473737,
      "position": 10.473067915690866
    }
  ],
  "yoyDateRange": {
    "start": "2025-01-04",
    "end": "2025-04-04"
  },
  "yoyTopQueries": [
    {
      "query": "kogan and disalvo",
      "clicks": 602,
      "impressions": 1949,
      "ctr": 0.30887634684453563,
      "position": 1.3324781939456132
    },
    {
      "query": "kogan & disalvo",
      "clicks": 141,
      "impressions": 364,
      "ctr": 0.3873626373626374,
      "position": 1.1373626373626373
    },
    {
      "query": "florida motorcycle accident lawyer",
      "clicks": 117,
      "impressions": 4570,
      "ctr": 0.025601750547045953,
      "position": 1.9341356673960612
    },
    {
      "query": "kogan disalvo",
      "clicks": 106,
      "impressions": 171,
      "ctr": 0.6198830409356725,
      "position": 1.0058479532163742
    },
    {
      "query": "motorcycle accident lawyer in florida",
      "clicks": 95,
      "impressions": 194,
      "ctr": 0.4896907216494845,
      "position": 1.4536082474226804
    },
    {
      "query": "motorcycle lawyer florida motorcycle accident",
      "clicks": 86,
      "impressions": 90,
      "ctr": 0.9555555555555556,
      "position": 1.5333333333333332
    },
    {
      "query": "motorcycle accident florida lawyer",
      "clicks": 76,
      "impressions": 119,
      "ctr": 0.6386554621848739,
      "position": 1.3445378151260505
    },
    {
      "query": "personal injury lawyer",
      "clicks": 54,
      "impressions": 21314,
      "ctr": 0.0025335460260861404,
      "position": 11.735807450502017
    },
    {
      "query": "personal injury lawyer west palm beach",
      "clicks": 53,
      "impressions": 1900,
      "ctr": 0.027894736842105264,
      "position": 20.338421052631578
    },
    {
      "query": "personal injury attorney",
      "clicks": 52,
      "impressions": 16827,
      "ctr": 0.0030902715873298865,
      "position": 12.088191596838415
    },
    {
      "query": "personal injury lawyer fort lauderdale",
      "clicks": 52,
      "impressions": 2383,
      "ctr": 0.021821233738984473,
      "position": 48.40704993705413
    },
    {
      "query": "kogan injury law",
      "clicks": 51,
      "impressions": 71,
      "ctr": 0.7183098591549296,
      "position": 1.0140845070422535
    },
    {
      "query": "car accident lawyer lantana fl",
      "clicks": 46,
      "impressions": 95,
      "ctr": 0.4842105263157895,
      "position": 3.463157894736842
    },
    {
      "query": "personal injury attorney delray beach",
      "clicks": 45,
      "impressions": 561,
      "ctr": 0.08021390374331551,
      "position": 7.737967914438503
    },
    {
      "query": "personal injury lawyers boca raton",
      "clicks": 45,
      "impressions": 595,
      "ctr": 0.07563025210084033,
      "position": 14.042016806722689
    },
    {
      "query": "injury lawyer",
      "clicks": 43,
      "impressions": 11255,
      "ctr": 0.0038205242114615727,
      "position": 12.12767658818303
    },
    {
      "query": "kogan & disalvo, p.a.",
      "clicks": 41,
      "impressions": 64,
      "ctr": 0.640625,
      "position": 1
    },
    {
      "query": "tampa personal injury lawyer",
      "clicks": 41,
      "impressions": 5169,
      "ctr": 0.007931901721803056,
      "position": 58.002514993228864
    },
    {
      "query": "personal injury lawyers st petersburg florida",
      "clicks": 39,
      "impressions": 76,
      "ctr": 0.5131578947368421,
      "position": 42.30263157894737
    },
    {
      "query": "motorcycle accident lawyer fl",
      "clicks": 37,
      "impressions": 186,
      "ctr": 0.1989247311827957,
      "position": 1.543010752688172
    },
    {
      "query": "personal injury attorneys",
      "clicks": 37,
      "impressions": 4673,
      "ctr": 0.007917825807832228,
      "position": 18.428418574791355
    },
    {
      "query": "darryl kogan",
      "clicks": 34,
      "impressions": 72,
      "ctr": 0.4722222222222222,
      "position": 1.0138888888888888
    },
    {
      "query": "car accident lawyer lantana",
      "clicks": 33,
      "impressions": 154,
      "ctr": 0.21428571428571427,
      "position": 7.461038961038961
    },
    {
      "query": "kogan & disalvo personal injury lawyers",
      "clicks": 33,
      "impressions": 749,
      "ctr": 0.044058744993324434,
      "position": 1.389853137516689
    },
    {
      "query": "south florida motorcycle accident lawyer",
      "clicks": 33,
      "impressions": 195,
      "ctr": 0.16923076923076924,
      "position": 3.6615384615384614
    },
    {
      "query": "personal injury lawyers",
      "clicks": 32,
      "impressions": 5141,
      "ctr": 0.0062244699474810344,
      "position": 13.126823575179927
    },
    {
      "query": "kogan and disalvo boynton",
      "clicks": 31,
      "impressions": 208,
      "ctr": 0.14903846153846154,
      "position": 1.0480769230769231
    },
    {
      "query": "injury attorney",
      "clicks": 29,
      "impressions": 9162,
      "ctr": 0.0031652477624972714,
      "position": 13.04736956996289
    },
    {
      "query": "kogan and disalvo boynton beach",
      "clicks": 27,
      "impressions": 110,
      "ctr": 0.24545454545454545,
      "position": 1.018181818181818
    },
    {
      "query": "motorcycle accident lawyer florida",
      "clicks": 27,
      "impressions": 1191,
      "ctr": 0.022670025188916875,
      "position": 1.8312342569269522
    },
    {
      "query": "fort lauderdale personal injury lawyer",
      "clicks": 26,
      "impressions": 3715,
      "ctr": 0.006998654104979811,
      "position": 57.86164199192463
    },
    {
      "query": "injury lawyers",
      "clicks": 26,
      "impressions": 4065,
      "ctr": 0.0063960639606396065,
      "position": 15.529643296432964
    },
    {
      "query": "kogan & disalvo boynton beach",
      "clicks": 25,
      "impressions": 64,
      "ctr": 0.390625,
      "position": 1
    },
    {
      "query": "kogan and disalvo stuart",
      "clicks": 24,
      "impressions": 251,
      "ctr": 0.09561752988047809,
      "position": 1.00398406374502
    },
    {
      "query": "jay london attorney",
      "clicks": 21,
      "impressions": 51,
      "ctr": 0.4117647058823529,
      "position": 1
    },
    {
      "query": "fort lauderdale personal injury attorney",
      "clicks": 20,
      "impressions": 2677,
      "ctr": 0.007471049682480389,
      "position": 41.41912588718715
    },
    {
      "query": "how do i look up an accident report in florida",
      "clicks": 18,
      "impressions": 675,
      "ctr": 0.02666666666666667,
      "position": 3.903703703703704
    },
    {
      "query": "injury attorneys",
      "clicks": 18,
      "impressions": 3289,
      "ctr": 0.005472788081483734,
      "position": 18.300395256916996
    },
    {
      "query": "todd baker attorney florida",
      "clicks": 18,
      "impressions": 36,
      "ctr": 0.5,
      "position": 1
    },
    {
      "query": "tiffany fanelli",
      "clicks": 17,
      "impressions": 166,
      "ctr": 0.10240963855421686,
      "position": 3.716867469879518
    },
    {
      "query": "florida personal injury lawyers",
      "clicks": 14,
      "impressions": 2748,
      "ctr": 0.005094614264919942,
      "position": 33.29985443959243
    },
    {
      "query": "paul silvestri",
      "clicks": 14,
      "impressions": 212,
      "ctr": 0.0660377358490566,
      "position": 3.797169811320755
    },
    {
      "query": "elen krut",
      "clicks": 13,
      "impressions": 23,
      "ctr": 0.5652173913043478,
      "position": 1.0869565217391304
    },
    {
      "query": "lakeland injury attorney",
      "clicks": 13,
      "impressions": 588,
      "ctr": 0.022108843537414966,
      "position": 26.67517006802721
    },
    {
      "query": "palm bay car accident lawyer",
      "clicks": 13,
      "impressions": 586,
      "ctr": 0.02218430034129693,
      "position": 1.7986348122866893
    },
    {
      "query": "personal injury law firm",
      "clicks": 13,
      "impressions": 2779,
      "ctr": 0.004677941705649514,
      "position": 14.646635480388628
    },
    {
      "query": "personal injury lawyers florida",
      "clicks": 13,
      "impressions": 1236,
      "ctr": 0.010517799352750809,
      "position": 33.730582524271846
    },
    {
      "query": "catastrophic injury lawyer",
      "clicks": 12,
      "impressions": 4316,
      "ctr": 0.0027803521779425394,
      "position": 15.663577386468953
    },
    {
      "query": "delray beach slip and fall lawyer",
      "clicks": 12,
      "impressions": 332,
      "ctr": 0.03614457831325301,
      "position": 5.198795180722891
    },
    {
      "query": "injury law firm",
      "clicks": 12,
      "impressions": 1025,
      "ctr": 0.011707317073170732,
      "position": 17.20780487804878
    },
    {
      "query": "kogan and disalvo reviews",
      "clicks": 12,
      "impressions": 95,
      "ctr": 0.12631578947368421,
      "position": 1.2105263157894737
    },
    {
      "query": "medical malpractice attorneys",
      "clicks": 12,
      "impressions": 2377,
      "ctr": 0.005048380311316786,
      "position": 23.202776609171224
    },
    {
      "query": "personal injury attorney fort lauderdale",
      "clicks": 12,
      "impressions": 1666,
      "ctr": 0.007202881152460984,
      "position": 48.49639855942377
    },
    {
      "query": "personal injury attorney tampa",
      "clicks": 12,
      "impressions": 3451,
      "ctr": 0.0034772529701535787,
      "position": 41.55288322225442
    },
    {
      "query": "personal injury lawyer delray beach",
      "clicks": 12,
      "impressions": 758,
      "ctr": 0.0158311345646438,
      "position": 4.701846965699208
    },
    {
      "query": "personal injury lawyer vero beach",
      "clicks": 12,
      "impressions": 1046,
      "ctr": 0.011472275334608031,
      "position": 5.735181644359464
    },
    {
      "query": "personal injury lawyers fort lauderdale",
      "clicks": 12,
      "impressions": 559,
      "ctr": 0.02146690518783542,
      "position": 38.49194991055456
    },
    {
      "query": "st petersburg wrongful death lawyer",
      "clicks": 12,
      "impressions": 381,
      "ctr": 0.031496062992125984,
      "position": 55.93175853018373
    },
    {
      "query": "ted disalvo",
      "clicks": 12,
      "impressions": 47,
      "ctr": 0.2553191489361702,
      "position": 1.9361702127659575
    },
    {
      "query": "motorcycle accident lawyer spring hill",
      "clicks": 11,
      "impressions": 678,
      "ctr": 0.016224188790560472,
      "position": 20.587020648967552
    },
    {
      "query": "personal injury attorney west palm beach",
      "clicks": 11,
      "impressions": 1633,
      "ctr": 0.006736068585425597,
      "position": 17.864666258420087
    },
    {
      "query": "personal injury attorneys florida",
      "clicks": 11,
      "impressions": 1114,
      "ctr": 0.009874326750448833,
      "position": 26.984739676840217
    },
    {
      "query": "personal injury lawyer near me",
      "clicks": 11,
      "impressions": 3964,
      "ctr": 0.0027749747729566097,
      "position": 21.630171543895056
    },
    {
      "query": "personal injury lawyer st petersburg fl",
      "clicks": 11,
      "impressions": 1647,
      "ctr": 0.006678809957498482,
      "position": 32.862173649058896
    },
    {
      "query": "personal injury lawyers in florida",
      "clicks": 11,
      "impressions": 1261,
      "ctr": 0.008723235527359239,
      "position": 26.549563838223634
    },
    {
      "query": "st. petersburg personal injury lawyer",
      "clicks": 11,
      "impressions": 1476,
      "ctr": 0.007452574525745257,
      "position": 33.887533875338754
    },
    {
      "query": "boynton beach car accident whiplash",
      "clicks": 10,
      "impressions": 35,
      "ctr": 0.2857142857142857,
      "position": 44.22857142857143
    },
    {
      "query": "can at fault driver sue me",
      "clicks": 10,
      "impressions": 65,
      "ctr": 0.15384615384615385,
      "position": 3.2
    },
    {
      "query": "car accident injury lawyer boynton beach",
      "clicks": 10,
      "impressions": 299,
      "ctr": 0.033444816053511704,
      "position": 2.160535117056856
    },
    {
      "query": "florida crash portal today",
      "clicks": 10,
      "impressions": 533,
      "ctr": 0.01876172607879925,
      "position": 6.818011257035647
    },
    {
      "query": "florida drone laws",
      "clicks": 10,
      "impressions": 710,
      "ctr": 0.014084507042253521,
      "position": 8.456338028169014
    },
    {
      "query": "injury lawyer in tampa",
      "clicks": 10,
      "impressions": 472,
      "ctr": 0.0211864406779661,
      "position": 55.766949152542374
    },
    {
      "query": "kogan & disalvo pa",
      "clicks": 10,
      "impressions": 26,
      "ctr": 0.38461538461538464,
      "position": 1.1153846153846154
    },
    {
      "query": "palm bay slip and fall lawyers",
      "clicks": 10,
      "impressions": 120,
      "ctr": 0.08333333333333333,
      "position": 1.6166666666666667
    },
    {
      "query": "personal injury lawyer st. petersburg fl",
      "clicks": 10,
      "impressions": 504,
      "ctr": 0.01984126984126984,
      "position": 33.46825396825397
    },
    {
      "query": "st petersburg personal injury attorney",
      "clicks": 10,
      "impressions": 1359,
      "ctr": 0.007358351729212656,
      "position": 30.80868285504047
    },
    {
      "query": "tampa injury lawyers",
      "clicks": 10,
      "impressions": 840,
      "ctr": 0.011904761904761904,
      "position": 60.84404761904762
    },
    {
      "query": "boynton beach injury lawyer",
      "clicks": 9,
      "impressions": 1497,
      "ctr": 0.006012024048096192,
      "position": 2.6820307281229123
    },
    {
      "query": "boynton beach personal injury lawyers",
      "clicks": 9,
      "impressions": 261,
      "ctr": 0.034482758620689655,
      "position": 2.157088122605364
    },
    {
      "query": "boynton injury lawyer",
      "clicks": 9,
      "impressions": 302,
      "ctr": 0.029801324503311258,
      "position": 2.178807947019868
    },
    {
      "query": "delray beach personal injury lawyer",
      "clicks": 9,
      "impressions": 832,
      "ctr": 0.010817307692307692,
      "position": 8.216346153846153
    },
    {
      "query": "florida personal injury attorney",
      "clicks": 9,
      "impressions": 3744,
      "ctr": 0.002403846153846154,
      "position": 37.66613247863248
    },
    {
      "query": "florida personal injury attorneys",
      "clicks": 9,
      "impressions": 1096,
      "ctr": 0.008211678832116789,
      "position": 28.829379562043794
    },
    {
      "query": "lakeland personal injury lawyer",
      "clicks": 9,
      "impressions": 1789,
      "ctr": 0.005030743432084964,
      "position": 26.470095025153718
    },
    {
      "query": "lawyer for personal injury",
      "clicks": 9,
      "impressions": 278,
      "ctr": 0.03237410071942446,
      "position": 28.111510791366907
    },
    {
      "query": "personal injury attorney fort lauderdale fl",
      "clicks": 9,
      "impressions": 344,
      "ctr": 0.02616279069767442,
      "position": 63.7906976744186
    },
    {
      "query": "personal injury lawyer boca",
      "clicks": 9,
      "impressions": 257,
      "ctr": 0.03501945525291829,
      "position": 14.544747081712062
    },
    {
      "query": "personal injury lawyer in boca raton",
      "clicks": 9,
      "impressions": 695,
      "ctr": 0.012949640287769784,
      "position": 14.607194244604317
    },
    {
      "query": "st petersburg injury lawyer",
      "clicks": 9,
      "impressions": 1204,
      "ctr": 0.007475083056478406,
      "position": 37.29318936877076
    },
    {
      "query": "st petersburg slip and fall lawyer",
      "clicks": 9,
      "impressions": 1077,
      "ctr": 0.008356545961002786,
      "position": 18.152274837511605
    },
    {
      "query": "stuart fl car accident lawyer",
      "clicks": 9,
      "impressions": 62,
      "ctr": 0.14516129032258066,
      "position": 3.6451612903225805
    },
    {
      "query": "tampa injury attorney",
      "clicks": 9,
      "impressions": 1641,
      "ctr": 0.005484460694698354,
      "position": 72.81109079829372
    },
    {
      "query": "what happens if someone sues you for more than your insurance covers in florida",
      "clicks": 9,
      "impressions": 281,
      "ctr": 0.03202846975088968,
      "position": 4.355871886120997
    },
    {
      "query": "boynton beach workplace accident",
      "clicks": 8,
      "impressions": 40,
      "ctr": 0.2,
      "position": 15.65
    },
    {
      "query": "can you sue for more than policy limits in florida",
      "clicks": 8,
      "impressions": 163,
      "ctr": 0.049079754601226995,
      "position": 1.9877300613496933
    },
    {
      "query": "car accident lawyer boynton beach",
      "clicks": 8,
      "impressions": 668,
      "ctr": 0.011976047904191617,
      "position": 2.860778443113772
    },
    {
      "query": "catastrophic injury attorney fort lauderdale",
      "clicks": 8,
      "impressions": 54,
      "ctr": 0.14814814814814814,
      "position": 12.166666666666666
    },
    {
      "query": "florida crash portal free",
      "clicks": 8,
      "impressions": 403,
      "ctr": 0.019851116625310174,
      "position": 7.344913151364764
    },
    {
      "query": "florida personal injury law firm",
      "clicks": 8,
      "impressions": 959,
      "ctr": 0.008342022940563087,
      "position": 17.19499478623566
    },
    {
      "query": "fort lauderdale personal injury attorneys",
      "clicks": 8,
      "impressions": 793,
      "ctr": 0.01008827238335435,
      "position": 56.733921815889026
    },
    {
      "query": "injury attorney boca raton fl",
      "clicks": 8,
      "impressions": 237,
      "ctr": 0.03375527426160337,
      "position": 13.518987341772151
    },
    {
      "query": "injury lawyer west palm beach",
      "clicks": 8,
      "impressions": 782,
      "ctr": 0.010230179028132993,
      "position": 19.130434782608695
    },
    {
      "query": "lakeland injury lawyer",
      "clicks": 8,
      "impressions": 896,
      "ctr": 0.008928571428571428,
      "position": 25.735491071428573
    },
    {
      "query": "lakeland slip and fall attorney",
      "clicks": 8,
      "impressions": 1692,
      "ctr": 0.004728132387706856,
      "position": 12.576241134751774
    },
    {
      "query": "personal injury attorney boca raton",
      "clicks": 8,
      "impressions": 1689,
      "ctr": 0.004736530491415038,
      "position": 13.703374777975133
    },
    {
      "query": "personal injury lawyers in fort lauderdale",
      "clicks": 8,
      "impressions": 121,
      "ctr": 0.06611570247933884,
      "position": 43.082644628099175
    },
    {
      "query": "st petersburg injury attorney",
      "clicks": 8,
      "impressions": 515,
      "ctr": 0.015533980582524271,
      "position": 40.89708737864078
    },
    {
      "query": "561-375-9500",
      "clicks": 7,
      "impressions": 63,
      "ctr": 0.1111111111111111,
      "position": 1
    },
    {
      "query": "accident attorney stuart",
      "clicks": 7,
      "impressions": 245,
      "ctr": 0.02857142857142857,
      "position": 9.33061224489796
    },
    {
      "query": "accident lawyer stuart",
      "clicks": 7,
      "impressions": 227,
      "ctr": 0.030837004405286344,
      "position": 8.687224669603523
    },
    {
      "query": "attorney personal injury",
      "clicks": 7,
      "impressions": 520,
      "ctr": 0.013461538461538462,
      "position": 41.5
    },
    {
      "query": "boca raton personal injury lawyer",
      "clicks": 7,
      "impressions": 3438,
      "ctr": 0.002036067481093659,
      "position": 14.12739965095986
    },
    {
      "query": "boca raton slip and fall lawyer",
      "clicks": 7,
      "impressions": 1543,
      "ctr": 0.004536616979909268,
      "position": 11.16202203499676
    },
    {
      "query": "boynton beach personal injury attorney",
      "clicks": 7,
      "impressions": 386,
      "ctr": 0.018134715025906734,
      "position": 2.6580310880829012
    },
    {
      "query": "boynton beach personal injury lawyer",
      "clicks": 7,
      "impressions": 2093,
      "ctr": 0.0033444816053511705,
      "position": 3.602962255136168
    },
    {
      "query": "car accident attorney delray beach",
      "clicks": 7,
      "impressions": 647,
      "ctr": 0.010819165378670788,
      "position": 9.341576506955178
    },
    {
      "query": "florida injury lawyer",
      "clicks": 7,
      "impressions": 979,
      "ctr": 0.007150153217568948,
      "position": 38.874361593462716
    },
    {
      "query": "florida insurance companies cancelling policies",
      "clicks": 7,
      "impressions": 25,
      "ctr": 0.28,
      "position": 2.2
    },
    {
      "query": "florida personal injury lawyer",
      "clicks": 7,
      "impressions": 4629,
      "ctr": 0.001512205659969756,
      "position": 24.83149708360337
    },
    {
      "query": "fort lauderdale personal injury lawyers",
      "clicks": 7,
      "impressions": 1184,
      "ctr": 0.0059121621621621625,
      "position": 39.94341216216216
    },
    {
      "query": "injury lawyer boynton beach",
      "clicks": 7,
      "impressions": 367,
      "ctr": 0.01907356948228883,
      "position": 2.8283378746594003
    },
    {
      "query": "injury lawyer florida",
      "clicks": 7,
      "impressions": 797,
      "ctr": 0.00878293601003764,
      "position": 47.10414052697616
    },
    {
      "query": "injury lawyer tampa",
      "clicks": 7,
      "impressions": 533,
      "ctr": 0.013133208255159476,
      "position": 48.37898686679174
    },
    {
      "query": "kogan and disalvo boca raton",
      "clicks": 7,
      "impressions": 34,
      "ctr": 0.20588235294117646,
      "position": 1.0294117647058822
    },
    {
      "query": "malpractice lawyer",
      "clicks": 7,
      "impressions": 2146,
      "ctr": 0.0032618825722274,
      "position": 42.41286113699907
    },
    {
      "query": "palm bay personal injury lawyer",
      "clicks": 7,
      "impressions": 635,
      "ctr": 0.011023622047244094,
      "position": 1.7244094488188977
    },
    {
      "query": "palm bay slip and fall lawyer",
      "clicks": 7,
      "impressions": 441,
      "ctr": 0.015873015873015872,
      "position": 1.63718820861678
    },
    {
      "query": "personal injury attorney boynton beach",
      "clicks": 7,
      "impressions": 627,
      "ctr": 0.011164274322169059,
      "position": 2.9266347687400316
    },
    {
      "query": "personal injury attorney st petersburg",
      "clicks": 7,
      "impressions": 572,
      "ctr": 0.012237762237762238,
      "position": 34.80944055944056
    },
    {
      "query": "personal injury lawyer attorney",
      "clicks": 7,
      "impressions": 123,
      "ctr": 0.056910569105691054,
      "position": 28.097560975609756
    },
    {
      "query": "personal injury lawyer in florida",
      "clicks": 7,
      "impressions": 673,
      "ctr": 0.010401188707280832,
      "position": 40.323922734026745
    },
    {
      "query": "personal injury lawyer tampa",
      "clicks": 7,
      "impressions": 4136,
      "ctr": 0.0016924564796905223,
      "position": 46.620164410058024
    },
    {
      "query": "stuart personal injury lawyer",
      "clicks": 7,
      "impressions": 741,
      "ctr": 0.009446693657219974,
      "position": 6.612685560053981
    },
    {
      "query": "tampa personal injury attorney",
      "clicks": 7,
      "impressions": 3723,
      "ctr": 0.0018802041364491002,
      "position": 51.681171098576414
    },
    {
      "query": "todd baker",
      "clicks": 7,
      "impressions": 108,
      "ctr": 0.06481481481481481,
      "position": 16.925925925925924
    },
    {
      "query": "tort lawyer",
      "clicks": 7,
      "impressions": 1034,
      "ctr": 0.006769825918762089,
      "position": 53.95744680851064
    },
    {
      "query": "west palm beach injury lawyer",
      "clicks": 7,
      "impressions": 982,
      "ctr": 0.007128309572301426,
      "position": 18.90427698574338
    },
    {
      "query": "west palm beach personal injury attorney",
      "clicks": 7,
      "impressions": 1494,
      "ctr": 0.004685408299866131,
      "position": 18.448460508701473
    },
    {
      "query": "back injury lawyer",
      "clicks": 6,
      "impressions": 3124,
      "ctr": 0.0019206145966709346,
      "position": 36.15749039692702
    },
    {
      "query": "boca raton injury lawyer",
      "clicks": 6,
      "impressions": 1781,
      "ctr": 0.003368893879842785,
      "position": 15.766423357664234
    },
    {
      "query": "car accident lawyer",
      "clicks": 6,
      "impressions": 13593,
      "ctr": 0.0004414036636504083,
      "position": 16.784521444861326
    },
    {
      "query": "car accident lawyer 33436 boynton beach fl",
      "clicks": 6,
      "impressions": 68,
      "ctr": 0.08823529411764706,
      "position": 3.4705882352941178
    },
    {
      "query": "car accident lawyer delray beach",
      "clicks": 6,
      "impressions": 1715,
      "ctr": 0.003498542274052478,
      "position": 9.387755102040817
    },
    {
      "query": "daniel collins attorney",
      "clicks": 6,
      "impressions": 29,
      "ctr": 0.20689655172413793,
      "position": 4.413793103448276
    },
    {
      "query": "do 1099 employees need workers' comp in florida",
      "clicks": 6,
      "impressions": 78,
      "ctr": 0.07692307692307693,
      "position": 4.717948717948718
    },
    {
      "query": "does progressive pay claims well",
      "clicks": 6,
      "impressions": 374,
      "ctr": 0.016042780748663103,
      "position": 7.724598930481283
    },
    {
      "query": "fort lauderdale injury lawyer",
      "clicks": 6,
      "impressions": 1013,
      "ctr": 0.005923000987166831,
      "position": 75.34846989141165
    },
    {
      "query": "insurance companies cancelling policies in florida",
      "clicks": 6,
      "impressions": 118,
      "ctr": 0.05084745762711865,
      "position": 2.923728813559322
    },
    {
      "query": "palm bay truck accident lawyer",
      "clicks": 6,
      "impressions": 104,
      "ctr": 0.057692307692307696,
      "position": 4.509615384615385
    },
    {
      "query": "personal injury attorney florida",
      "clicks": 6,
      "impressions": 3171,
      "ctr": 0.001892147587511826,
      "position": 33.53421633554084
    },
    {
      "query": "personal injury attorney st petersburg fl",
      "clicks": 6,
      "impressions": 716,
      "ctr": 0.008379888268156424,
      "position": 40.513966480446925
    },
    {
      "query": "personal injury attorney vero beach",
      "clicks": 6,
      "impressions": 216,
      "ctr": 0.027777777777777776,
      "position": 4.611111111111111
    },
    {
      "query": "personal injury lawyer lakeland",
      "clicks": 6,
      "impressions": 1236,
      "ctr": 0.0048543689320388345,
      "position": 25.537216828478964
    },
    {
      "query": "personal injury lawyer st. petersburg",
      "clicks": 6,
      "impressions": 807,
      "ctr": 0.007434944237918215,
      "position": 34.24163568773234
    },
    {
      "query": "st. petersburg wrongful death lawyer",
      "clicks": 6,
      "impressions": 643,
      "ctr": 0.00933125972006221,
      "position": 55.132192846034215
    },
    {
      "query": "tampa injury lawyer",
      "clicks": 6,
      "impressions": 2514,
      "ctr": 0.002386634844868735,
      "position": 59.89976133651551
    },
    {
      "query": "west palm beach personal injury lawyers",
      "clicks": 6,
      "impressions": 589,
      "ctr": 0.010186757215619695,
      "position": 16.89983022071307
    },
    {
      "query": "at fault driver suing me",
      "clicks": 5,
      "impressions": 119,
      "ctr": 0.04201680672268908,
      "position": 2.8235294117647056
    },
    {
      "query": "boca raton birth injury lawyer",
      "clicks": 5,
      "impressions": 778,
      "ctr": 0.006426735218508998,
      "position": 45.24807197943445
    },
    {
      "query": "car accident lawyer vero beach",
      "clicks": 5,
      "impressions": 1212,
      "ctr": 0.004125412541254125,
      "position": 6.415841584158416
    },
    {
      "query": "charles bowen attorney",
      "clicks": 5,
      "impressions": 25,
      "ctr": 0.2,
      "position": 4.96
    },
    {
      "query": "fatal motorcycle accident lawyer",
      "clicks": 5,
      "impressions": 86,
      "ctr": 0.05813953488372093,
      "position": 45.98837209302326
    },
    {
      "query": "injury attorney tampa",
      "clicks": 5,
      "impressions": 809,
      "ctr": 0.006180469715698393,
      "position": 56.778739184178
    },
    {
      "query": "kogan & disalvo p.a",
      "clicks": 5,
      "impressions": 8,
      "ctr": 0.625,
      "position": 1
    },
    {
      "query": "my own insurance company wants a recorded statement",
      "clicks": 5,
      "impressions": 136,
      "ctr": 0.03676470588235294,
      "position": 10.176470588235293
    },
    {
      "query": "personal injuries lawyer near me",
      "clicks": 5,
      "impressions": 133,
      "ctr": 0.03759398496240601,
      "position": 16.203007518796994
    },
    {
      "query": "personal injury attorney in fort lauderdale",
      "clicks": 5,
      "impressions": 153,
      "ctr": 0.032679738562091505,
      "position": 64.95424836601308
    },
    {
      "query": "personal injury attorney lakeland",
      "clicks": 5,
      "impressions": 566,
      "ctr": 0.0088339222614841,
      "position": 23.81095406360424
    },
    {
      "query": "personal injury attorney west bay",
      "clicks": 5,
      "impressions": 39,
      "ctr": 0.1282051282051282,
      "position": 4.794871794871795
    },
    {
      "query": "personal injury lawyer boca raton",
      "clicks": 5,
      "impressions": 2910,
      "ctr": 0.001718213058419244,
      "position": 15.7340206185567
    },
    {
      "query": "personal injury lawyer boynton beach",
      "clicks": 5,
      "impressions": 2081,
      "ctr": 0.002402691013935608,
      "position": 3.409899086977415
    },
    {
      "query": "slip and fall lawyer fort lauderdale",
      "clicks": 5,
      "impressions": 269,
      "ctr": 0.01858736059479554,
      "position": 26.635687732342006
    },
    {
      "query": "st petersburg personal injury lawyer",
      "clicks": 5,
      "impressions": 1960,
      "ctr": 0.002551020408163265,
      "position": 33.72295918367347
    },
    {
      "query": "todd baker attorney",
      "clicks": 5,
      "impressions": 31,
      "ctr": 0.16129032258064516,
      "position": 1.935483870967742
    },
    {
      "query": "are parents liable for 18 year-olds car accidents",
      "clicks": 4,
      "impressions": 26,
      "ctr": 0.15384615384615385,
      "position": 6.846153846153846
    },
    {
      "query": "auto accident lawyer stuart",
      "clicks": 4,
      "impressions": 233,
      "ctr": 0.017167381974248927,
      "position": 6.9742489270386265
    },
    {
      "query": "boca raton injury attorney",
      "clicks": 4,
      "impressions": 1362,
      "ctr": 0.002936857562408223,
      "position": 16.412628487518354
    },
    {
      "query": "boca raton motorcycle accident lawyer",
      "clicks": 4,
      "impressions": 1822,
      "ctr": 0.0021953896816684962,
      "position": 14.21953896816685
    },
    {
      "query": "boca raton personal injury attorneys",
      "clicks": 4,
      "impressions": 619,
      "ctr": 0.006462035541195477,
      "position": 11.751211631663974
    },
    {
      "query": "boca raton personal injury lawyers",
      "clicks": 4,
      "impressions": 1054,
      "ctr": 0.003795066413662239,
      "position": 13.190702087286528
    },
    {
      "query": "boynton beach back injury",
      "clicks": 4,
      "impressions": 19,
      "ctr": 0.21052631578947367,
      "position": 29.31578947368421
    },
    {
      "query": "car accident attorney west palm beach",
      "clicks": 4,
      "impressions": 2145,
      "ctr": 0.0018648018648018648,
      "position": 11.167365967365967
    },
    {
      "query": "car accident lawyer palm bay",
      "clicks": 4,
      "impressions": 738,
      "ctr": 0.005420054200542005,
      "position": 1.7398373983739837
    },
    {
      "query": "dan collins attorney",
      "clicks": 4,
      "impressions": 63,
      "ctr": 0.06349206349206349,
      "position": 5.682539682539683
    },
    {
      "query": "delray beach personal injury attorney",
      "clicks": 4,
      "impressions": 518,
      "ctr": 0.007722007722007722,
      "position": 9.150579150579151
    },
    {
      "query": "injury lawyer near me",
      "clicks": 4,
      "impressions": 2446,
      "ctr": 0.001635322976287817,
      "position": 19.01226492232216
    },
    {
      "query": "injury lawyer stuart",
      "clicks": 4,
      "impressions": 182,
      "ctr": 0.02197802197802198,
      "position": 5.0989010989010985
    },
    {
      "query": "insurance companies canceling policies in florida",
      "clicks": 4,
      "impressions": 38,
      "ctr": 0.10526315789473684,
      "position": 2.552631578947368
    },
    {
      "query": "kogan law",
      "clicks": 4,
      "impressions": 24,
      "ctr": 0.16666666666666666,
      "position": 3.9583333333333335
    },
    {
      "query": "lakeland slip and fall lawyer",
      "clicks": 4,
      "impressions": 964,
      "ctr": 0.004149377593360996,
      "position": 16.491701244813278
    },
    {
      "query": "mass tort lawyers",
      "clicks": 4,
      "impressions": 1435,
      "ctr": 0.0027874564459930314,
      "position": 62.38745644599303
    },
    {
      "query": "motorcycle lawyer motorcycle accident lawyers",
      "clicks": 4,
      "impressions": 8,
      "ctr": 0.5,
      "position": 3.25
    },
    {
      "query": "personal injury attorney st. petersburg",
      "clicks": 4,
      "impressions": 496,
      "ctr": 0.008064516129032258,
      "position": 34.61290322580645
    },
    {
      "query": "personal injury law firm west bay",
      "clicks": 4,
      "impressions": 66,
      "ctr": 0.06060606060606061,
      "position": 11.515151515151516
    },
    {
      "query": "personal injury lawyer in london",
      "clicks": 4,
      "impressions": 4,
      "ctr": 1,
      "position": 159.25
    },
    {
      "query": "personal injury lawyer st petersburg",
      "clicks": 4,
      "impressions": 1370,
      "ctr": 0.00291970802919708,
      "position": 33.10802919708029
    },
    {
      "query": "personal injury lawyer tampa fl",
      "clicks": 4,
      "impressions": 1705,
      "ctr": 0.002346041055718475,
      "position": 36.26862170087976
    },
    {
      "query": "st petersburg slip and fall attorney",
      "clicks": 4,
      "impressions": 1145,
      "ctr": 0.0034934497816593887,
      "position": 13.724890829694322
    },
    {
      "query": "st. petersburg personal injury attorney",
      "clicks": 4,
      "impressions": 892,
      "ctr": 0.004484304932735426,
      "position": 31.383408071748878
    },
    {
      "query": "stuart personal injury attorney",
      "clicks": 4,
      "impressions": 383,
      "ctr": 0.010443864229765013,
      "position": 4.323759791122715
    }
  ],
  "fetchedAt": "2026-04-07T17:41:55.855Z"
}